odoo/addons/stock_generate_putaway_from_inventory/README.rst
odoo/addons/stock_generate_putaway_from_inventory/__init__.py
odoo/addons/stock_generate_putaway_from_inventory/__manifest__.py
odoo/addons/stock_generate_putaway_from_inventory/i18n/fr.po
odoo/addons/stock_generate_putaway_from_inventory/i18n/stock_generate_putaway_from_inventory.pot
odoo/addons/stock_generate_putaway_from_inventory/models/__init__.py
odoo/addons/stock_generate_putaway_from_inventory/models/stock_inventory.py
odoo/addons/stock_generate_putaway_from_inventory/readme/CONTRIBUTORS.rst
odoo/addons/stock_generate_putaway_from_inventory/readme/DESCRIPTION.rst
odoo/addons/stock_generate_putaway_from_inventory/readme/USAGE.rst
odoo/addons/stock_generate_putaway_from_inventory/static/description/icon.png
odoo/addons/stock_generate_putaway_from_inventory/static/description/index.html
odoo/addons/stock_generate_putaway_from_inventory/tests/__init__.py
odoo/addons/stock_generate_putaway_from_inventory/tests/test_generate_putaway.py
odoo/addons/stock_generate_putaway_from_inventory/views/stock_inventory.xml
odoo12_addon_stock_generate_putaway_from_inventory-12.0.1.0.1.dist-info/METADATA
odoo12_addon_stock_generate_putaway_from_inventory-12.0.1.0.1.dist-info/WHEEL
odoo12_addon_stock_generate_putaway_from_inventory-12.0.1.0.1.dist-info/top_level.txt
odoo12_addon_stock_generate_putaway_from_inventory-12.0.1.0.1.dist-info/RECORD
